pdutil/__init__.py
pdutil/_version.py
pdutil/display/__init__.py
pdutil/display/display.py
pdutil/iter/__init__.py
pdutil/iter/iter.py
pdutil/serial/__init__.py
pdutil/serial/serial.py
pdutil/transform/__init__.py
pdutil/transform/transform.py
tests/__init__.py
tests/transform/__init__.py
tests/transform/test_or_by_masks.py
pdutil-0.0.11.dist-info/LICENSE
pdutil-0.0.11.dist-info/METADATA
pdutil-0.0.11.dist-info/WHEEL
pdutil-0.0.11.dist-info/top_level.txt
pdutil-0.0.11.dist-info/RECORD
